Prob_Dists_GB/Binomialdistribution.py
Prob_Dists_GB/Gaussiandistribution.py
Prob_Dists_GB/Generaldistribution.py
Prob_Dists_GB/__init__.py
Prob_Dists_GB-1.0.dist-info/LICENCE.txt
Prob_Dists_GB-1.0.dist-info/METADATA
Prob_Dists_GB-1.0.dist-info/WHEEL
Prob_Dists_GB-1.0.dist-info/top_level.txt
Prob_Dists_GB-1.0.dist-info/RECORD
